pygnata
