Metadata-Version: 1.1
Name: pygnata
Version: 0.0.4
Summary: Generator of projects tree from template
Home-page: https://github.com/joviaux/pygnata
Author: Alexandre LM, Dimitri S
Author-email: pygnata@tutanota.com
License: UNKNOWN
Platform: UNKNOWN
Classifier: Programming Language :: Python
Classifier: Development Status :: 4 - Beta
Classifier: License :: OSI Approved :: MIT License
Classifier: Natural Language :: French
Classifier: Operating System :: POSIX :: Linux
Classifier: Programming Language :: Python :: 3.4
Classifier: Topic :: Software Development
